Metadata-Version: 2.1
Name: python-call-graph
Version: 2.1.6
Summary: Python Call Graph is a library and command line tool that visualises the flow of your Python application.  This is a fork of the original, updated to work with Python 3.5 - 3.11 and from 2.1.4 3.8 - 3.13  See https://lewiscowles1986.github.io/py-call-graph/ for more information.
Home-page: http://pycallgraph.readthedocs.io/
Author: Gerald Kaszuba
Author-email: pycallgraph@gakman.com
License: 		    GNU GENERAL PUBLIC LICENSE
Classifier: Development Status :: 4 - Beta
Classifier: Intended Audience :: Developers
Classifier: License :: OSI Approved :: GNU General Public License (GPL)
Classifier: Natural Language :: English
Classifier: Operating System :: OS Independent
Classifier: Programming Language :: Python
Classifier: Programming Language :: Python :: 3
Classifier: Programming Language :: Python :: 3.8
Classifier: Programming Language :: Python :: 3.9
Classifier: Programming Language :: Python :: 3.10
Classifier: Programming Language :: Python :: 3.11
Classifier: Programming Language :: Python :: 3.12
Classifier: Programming Language :: Python :: 3.13
Classifier: Topic :: Software Development :: Libraries :: Python Modules
Classifier: Topic :: Software Development :: Testing
Classifier: Topic :: Software Development :: Debuggers
Provides-Extra: ipython
Provides-Extra: memory-psutil
License-File: LICENSE
